{"nm":"Main Scene","ddd":0,"h":500,"w":500,"meta":{"g":"@lottiefiles/creator 1.44.0"},"layers":[{"ty":4,"nm":"Calque_1-2","sr":1,"st":0,"op":150,"ip":0,"hd":false,"ln":"Calque_1-2","ddd":0,"bm":0,"hasMask":false,"ao":0,"ks":{"a":{"a":0,"k":[154.445,143.98]},"s":{"a":0,"k":[100,100]},"sk":{"a":0,"k":0},"p":{"a":0,"k":[252.91716559377824,246.0891227977205]},"r":{"a":1,"k":[{"o":{"x":0,"y":0},"i":{"x":0.36,"y":1},"s":[0],"t":0},{"o":{"x":0.65,"y":0},"i":{"x":1,"y":1},"s":[3],"t":10},{"s":[0],"t":33}]},"sa":{"a":0,"k":0},"o":{"a":0,"k":100}},"shapes":[{"ty":"gr","bm":0,"hd":false,"nm":"Group 1","it":[{"ty":"tr","a":{"a":0,"k":[154.77678700181104,181.99157642594463]},"s":{"a":0,"k":[100,100]},"sk":{"a":0,"k":0},"p":{"a":0,"k":[154.77678700181104,181.99157642594463]},"r":{"a":0,"k":0},"sa":{"a":0,"k":0},"o":{"a":0,"k":100}}]},{"ty":"gr","bm":0,"hd":false,"nm":"Group 3","it":[{"ty":"gr","bm":0,"hd":false,"nm":"Group 2","it":[{"ty":"sh","bm":0,"hd":false,"nm":"Path 1","d":1,"ks":{"a":0,"k":{"c":false,"i":[[0,0],[-8.129999999999995,0],[0,-7]],"o":[[0,-7],[8.129999999999995,0],[0,0]],"v":[[139.72,188.06],[154.44,175.38],[169.16,188.06]]}}},{"ty":"st","bm":0,"hd":false,"nm":"Stroke","lc":2,"lj":2,"ml":4,"o":{"a":0,"k":100},"w":{"a":0,"k":2},"c":{"a":0,"k":[0.1529,0.149,0.2667]}},{"ty":"tr","a":{"a":0,"k":[154.77678700181104,181.99157642594463]},"s":{"a":0,"k":[100,100]},"sk":{"a":0,"k":0},"p":{"a":0,"k":[154.77678700181104,181.99157642594463]},"r":{"a":0,"k":0},"sa":{"a":0,"k":0},"o":{"a":0,"k":100}}]},{"ty":"gr","bm":0,"hd":false,"nm":"Group 4","it":[{"ty":"gr","bm":0,"hd":false,"nm":"Group 5","it":[{"ty":"gr","bm":0,"hd":false,"nm":"Group 6","it":[{"ty":"el","bm":0,"hd":false,"nm":"Ellipse 1","d":1,"p":{"a":0,"k":[112.32,186.61]},"s":{"a":0,"k":[55.42,52.5]}},{"ty":"st","bm":0,"hd":false,"nm":"Stroke","lc":2,"lj":2,"ml":4,"o":{"a":0,"k":100},"w":{"a":0,"k":2},"c":{"a":0,"k":[0.1529,0.149,0.2667]}},{"ty":"tr","a":{"a":0,"k":[0,0]},"s":{"a":0,"k":[100,100]},"sk":{"a":0,"k":0},"p":{"a":0,"k":[0,0]},"r":{"a":0,"k":0},"sa":{"a":0,"k":0},"o":{"a":0,"k":100}}]},{"ty":"tr","a":{"a":0,"k":[0,0]},"s":{"a":0,"k":[100,100]},"sk":{"a":0,"k":0},"p":{"a":0,"k":[0,0]},"r":{"a":0,"k":0},"sa":{"a":0,"k":0},"o":{"a":0,"k":100}}]},{"ty":"gr","bm":0,"hd":false,"nm":"Group 7","it":[{"ty":"gr","bm":0,"hd":false,"nm":"Group 8","it":[{"ty":"sh","bm":0,"hd":false,"nm":"Path 2","d":1,"ks":{"a":0,"k":{"c":true,"i":[[0,0],[-8.289999999999992,-2.8899999999999864],[8.290000000000006,0],[0,-5.069999999999993]],"o":[[7.859999999999999,-2.8499999999999943],[0,-5.0800000000000125],[-8.290000000000006,0],[0,0]],"v":[[96.39,180.62],[126.41,180.62],[111.39999999999999,171.43],[96.38999999999999,180.62]]}}},{"ty":"st","bm":0,"hd":false,"nm":"Stroke","lc":1,"lj":1,"ml":10,"o":{"a":0,"k":100},"w":{"a":0,"k":3},"c":{"a":0,"k":[0.898,0.7412,0.702]}},{"ty":"fl","bm":0,"hd":false,"nm":"Fill","c":{"a":0,"k":[0.949,0.8549,0.8275]},"r":1,"o":{"a":0,"k":100}},{"ty":"tr","a":{"a":0,"k":[0,0]},"s":{"a":0,"k":[100,100]},"sk":{"a":0,"k":0},"p":{"a":0,"k":[0,0]},"r":{"a":0,"k":0},"sa":{"a":0,"k":0},"o":{"a":0,"k":100}}]},{"ty":"tr","a":{"a":0,"k":[111.08174277100629,176.2937423937885]},"s":{"a":0,"k":[100,100]},"sk":{"a":0,"k":0},"p":{"a":0,"k":[111.08174277100629,176.2937423937885]},"r":{"a":0,"k":0},"sa":{"a":0,"k":0},"o":{"a":0,"k":100}}]},{"ty":"gr","bm":0,"hd":false,"nm":"Group 9","it":[{"ty":"gr","bm":0,"hd":false,"nm":"Group 10","it":[{"ty":"el","bm":0,"hd":false,"nm":"Ellipse 2","d":1,"p":{"a":0,"k":[111.4,182.91]},"s":{"a":0,"k":[4.76,4.76]}},{"ty":"fl","bm":0,"hd":false,"nm":"Fill","c":{"a":0,"k":[0.1137,0.1137,0.1059]},"r":1,"o":{"a":0,"k":100}},{"ty":"tr","a":{"a":0,"k":[0,0]},"s":{"a":0,"k":[100,100]},"sk":{"a":0,"k":0},"p":{"a":0,"k":[0,0]},"r":{"a":0,"k":0},"sa":{"a":0,"k":0},"o":{"a":0,"k":100}}]},{"ty":"gr","bm":0,"hd":false,"nm":"Group 11","it":[{"ty":"el","bm":0,"hd":false,"nm":"Ellipse 3","d":1,"p":{"a":0,"k":[111.4,182.91]},"s":{"a":0,"k":[11.3,11.06]}},{"ty":"st","bm":0,"hd":false,"nm":"Stroke","lc":2,"lj":2,"ml":4,"o":{"a":0,"k":100},"w":{"a":0,"k":2},"c":{"a":0,"k":[0.4745,0.4745,0.7216]}},{"ty":"fl","bm":0,"hd":false,"nm":"Fill","c":{"a":0,"k":[0.4745,0.4745,0.7216]},"r":1,"o":{"a":0,"k":100}},{"ty":"tr","a":{"a":0,"k":[0,0]},"s":{"a":0,"k":[100,100]},"sk":{"a":0,"k":0},"p":{"a":0,"k":[0,0]},"r":{"a":0,"k":0},"sa":{"a":0,"k":0},"o":{"a":0,"k":100}}]},{"ty":"tr","a":{"a":0,"k":[0,0]},"s":{"a":0,"k":[100,100]},"sk":{"a":0,"k":0},"p":{"a":0,"k":[0,0]},"r":{"a":0,"k":0},"sa":{"a":0,"k":0},"o":{"a":0,"k":100}}]},{"ty":"gr","bm":0,"hd":false,"nm":"Group 12","it":[{"ty":"gr","bm":0,"hd":false,"nm":"Group 13","it":[{"ty":"el","bm":0,"hd":false,"nm":"Ellipse 4","d":1,"p":{"a":0,"k":[111.4,182.08]},"s":{"a":0,"k":[30.02,18.38]}},{"ty":"st","bm":0,"hd":false,"nm":"Stroke","lc":1,"lj":1,"ml":10,"o":{"a":0,"k":100},"w":{"a":0,"k":3},"c":{"a":0,"k":[0.898,0.7412,0.702]}},{"ty":"fl","bm":0,"hd":false,"nm":"Fill","c":{"a":0,"k":[1,1,1]},"r":1,"o":{"a":0,"k":100}},{"ty":"tr","a":{"a":0,"k":[0,0]},"s":{"a":0,"k":[100,100]},"sk":{"a":0,"k":0},"p":{"a":0,"k":[0,0]},"r":{"a":0,"k":0},"sa":{"a":0,"k":0},"o":{"a":0,"k":100}}]},{"ty":"tr","a":{"a":0,"k":[0,0]},"s":{"a":0,"k":[100,100]},"sk":{"a":0,"k":0},"p":{"a":0,"k":[0,0]},"r":{"a":0,"k":0},"sa":{"a":0,"k":0},"o":{"a":0,"k":100}}]},{"ty":"tr","a":{"a":0,"k":[111.90767993009743,186.49042726520946]},"s":{"a":0,"k":[100,100]},"sk":{"a":0,"k":0},"p":{"a":0,"k":[111.90767993009743,186.49042726520946]},"r":{"a":0,"k":0},"sa":{"a":0,"k":0},"o":{"a":0,"k":100}}]},{"ty":"gr","bm":0,"hd":false,"nm":"Group 14","it":[{"ty":"gr","bm":0,"hd":false,"nm":"Group 15","it":[{"ty":"gr","bm":0,"hd":false,"nm":"Group 16","it":[{"ty":"el","bm":0,"hd":false,"nm":"Ellipse 5","d":1,"p":{"a":0,"k":[196.57,186.61]},"s":{"a":0,"k":[55.42,52.5]}},{"ty":"st","bm":0,"hd":false,"nm":"Stroke","lc":2,"lj":2,"ml":4,"o":{"a":0,"k":100},"w":{"a":0,"k":2},"c":{"a":0,"k":[0.1529,0.149,0.2667]}},{"ty":"tr","a":{"a":0,"k":[0,0]},"s":{"a":0,"k":[100,100]},"sk":{"a":0,"k":0},"p":{"a":0,"k":[0,0]},"r":{"a":0,"k":0},"sa":{"a":0,"k":0},"o":{"a":0,"k":100}}]},{"ty":"tr","a":{"a":0,"k":[196.7502925687893,186.8246291344569]},"s":{"a":0,"k":[100,100]},"sk":{"a":0,"k":0},"p":{"a":0,"k":[196.7502925687893,186.8246291344569]},"r":{"a":0,"k":0},"sa":{"a":0,"k":0},"o":{"a":0,"k":100}}]},{"ty":"gr","bm":0,"hd":false,"nm":"Group 17","it":[{"ty":"gr","bm":0,"hd":false,"nm":"Group 18","it":[{"ty":"sh","bm":0,"hd":false,"nm":"Path 3","d":1,"ks":{"a":1,"k":[{"o":{"x":0.167,"y":0.167},"i":{"x":0.833,"y":0.833},"s":[{"c":false,"i":[[0,0],[8.29000000000002,-2.8899999999999864],[-8.289999999999992,0],[0,-5.069999999999993]],"o":[[-7.860000000000014,-2.8499999999999943],[0,-5.0800000000000125],[8.289999999999992,0],[0,0]],"v":[[212.5,180.62],[182.48,180.62],[197.48999999999998,171.43],[212.49999999999997,180.62]]}],"t":0},{"o":{"x":0.167,"y":0.167},"i":{"x":0.833,"y":0.833},"s":[{"c":false,"i":[[-1.1102230246251565e-16,-1.7763568394002505e-15],[6.486859846343805,17.692640321258864],[-8.289999999999992,0],[0,-5.069999999999993]],"o":[[0.6175633868825798,7.236758780473792],[0,-5.0800000000000125],[8.289999999999992,0],[0,0]],"v":[[212.50000000000023,180.61999999999998],[182.48000000000002,180.62000000000015],[197.50270105578392,180.34647086393815],[212.5000000000001,180.61999999999998]]}],"t":21},{"s":[{"c":false,"i":[[0,0],[8.29000000000002,-2.8899999999999864],[-8.289999999999992,0],[0,-5.069999999999993]],"o":[[-7.860000000000014,-2.8499999999999943],[0,-5.0800000000000125],[8.289999999999992,0],[0,0]],"v":[[212.5,180.62],[182.48,180.62],[197.48999999999998,171.43],[212.49999999999997,180.62]]}],"t":33}]}},{"ty":"st","bm":0,"hd":false,"nm":"Stroke","lc":1,"lj":1,"ml":10,"o":{"a":0,"k":100},"w":{"a":0,"k":3},"c":{"a":0,"k":[0.898,0.7412,0.702]}},{"ty":"fl","bm":0,"hd":false,"nm":"Fill","c":{"a":0,"k":[0.949,0.8549,0.8275]},"r":1,"o":{"a":0,"k":100}},{"ty":"tr","a":{"a":0,"k":[0,0]},"s":{"a":0,"k":[100,100]},"sk":{"a":0,"k":0},"p":{"a":0,"k":[0,0]},"r":{"a":0,"k":0},"sa":{"a":0,"k":0},"o":{"a":0,"k":100}}]},{"ty":"tr","a":{"a":0,"k":[197.17322658487143,175.78736829591364]},"s":{"a":0,"k":[100,100]},"sk":{"a":0,"k":0},"p":{"a":0,"k":[197.17322658487143,175.78736829591364]},"r":{"a":0,"k":0},"sa":{"a":0,"k":0},"o":{"a":0,"k":100}}]},{"ty":"gr","bm":0,"hd":false,"nm":"Group 19","it":[{"ty":"gr","bm":0,"hd":false,"nm":"Group 20","it":[{"ty":"el","bm":0,"hd":false,"nm":"Ellipse 6","d":1,"p":{"a":0,"k":[197.49,182.91]},"s":{"a":0,"k":[4.76,4.76]}},{"ty":"fl","bm":0,"hd":false,"nm":"Fill","c":{"a":0,"k":[0.1137,0.1137,0.1059]},"r":1,"o":{"a":0,"k":100}},{"ty":"tr","a":{"a":0,"k":[197.45,182.98]},"s":{"a":0,"k":[100,100]},"sk":{"a":0,"k":0},"p":{"a":0,"k":[197.45,182.98]},"r":{"a":0,"k":0},"sa":{"a":0,"k":0},"o":{"a":0,"k":100}}]},{"ty":"gr","bm":0,"hd":false,"nm":"Group 21","it":[{"ty":"sh","bm":0,"hd":false,"nm":"Ellipse 7","d":1,"ks":{"a":1,"k":[{"o":{"x":0.167,"y":0.167},"i":{"x":0.833,"y":0.833},"s":[{"c":true,"i":[[-3.118235,0],[0,-3.0520069999999997],[3.118235,0],[0,3.0520069999999997]],"o":[[3.118235,0],[0,3.0520069999999997],[-3.118235,0],[0,-3.0520069999999997]],"v":[[197.49,177.38],[203.14000000000001,182.91],[197.49,188.44],[191.84,182.91]]}],"t":0},{"o":{"x":0.167,"y":0.167},"i":{"x":0.833,"y":0.833},"s":[{"c":true,"i":[[-3.118235,0],[0,-3.0520069999999997],[3.118235,0],[0,3.0520069999999997]],"o":[[3.118235,0],[0,3.0520069999999997],[-3.118235,0],[0,-3.0520069999999997]],"v":[[197.8791635598049,182.04990046124348],[203.14000000000004,182.9100000000001],[198.205299002556,185.96744960867593],[191.8400000000001,182.91]]}],"t":16},{"s":[{"c":true,"i":[[-3.118235,0],[0,-3.0520069999999997],[3.118235,0],[0,3.0520069999999997]],"o":[[3.118235,0],[0,3.0520069999999997],[-3.118235,0],[0,-3.0520069999999997]],"v":[[197.49,177.38],[203.14000000000001,182.91],[197.49,188.44],[191.84,182.91]]}],"t":33}]}},{"ty":"st","bm":0,"hd":false,"nm":"Stroke","lc":2,"lj":2,"ml":4,"o":{"a":0,"k":100},"w":{"a":0,"k":2},"c":{"a":0,"k":[0.4745,0.4745,0.7216]}},{"ty":"fl","bm":0,"hd":false,"nm":"Fill","c":{"a":0,"k":[0.4745,0.4745,0.7216]},"r":1,"o":{"a":0,"k":100}},{"ty":"tr","a":{"a":0,"k":[0,0]},"s":{"a":0,"k":[100,100]},"sk":{"a":0,"k":0},"p":{"a":0,"k":[0,0]},"r":{"a":0,"k":0},"sa":{"a":0,"k":0},"o":{"a":0,"k":100}}]},{"ty":"tr","a":{"a":0,"k":[197.53957827857204,182.7777750391957]},"s":{"a":0,"k":[100,100]},"sk":{"a":0,"k":0},"p":{"a":0,"k":[197.53957827857204,182.7777750391957]},"r":{"a":0,"k":0},"sa":{"a":0,"k":0},"o":{"a":0,"k":100}}]},{"ty":"gr","bm":0,"hd":false,"nm":"Group 22","it":[{"ty":"gr","bm":0,"hd":false,"nm":"Group 23","it":[{"ty":"sh","bm":0,"hd":false,"nm":"Ellipse 8","d":1,"ks":{"a":1,"k":[{"o":{"x":0.167,"y":0.167},"i":{"x":0.833,"y":0.833},"s":[{"c":false,"i":[[-8.284018999999999,0],[0,-5.071960999999999],[8.284018999999999,0],[0,5.071960999999999]],"o":[[8.284018999999999,0],[0,5.071960999999999],[-8.284018999999999,0],[0,-5.071960999999999]],"v":[[197.49,172.89000000000001],[212.5,182.08],[197.49,191.27],[182.48000000000002,182.08]]}],"t":0},{"o":{"x":0.167,"y":0.167},"i":{"x":0.833,"y":0.833},"s":[{"c":false,"i":[[-8.284018999999999,0],[0,-5.071960999999999],[4.398669740407968,0.22489579977496987],[0,5.071960999999999]],"o":[[8.284018999999999,0],[0,5.071960999999999],[-4.398669740407968,-0.22489579977496987],[0,-5.071960999999999]],"v":[[196.22076432985415,183.28559355985234],[212.50000000000006,182.08],[196.80736663957896,188.9987295133307],[182.48000000000025,182.08000000000024]]}],"t":16},{"s":[{"c":false,"i":[[-8.284018999999999,0],[0,-5.071960999999999],[8.284018999999999,0],[0,5.071960999999999]],"o":[[8.284018999999999,0],[0,5.071960999999999],[-8.284018999999999,0],[0,-5.071960999999999]],"v":[[197.49,172.89000000000001],[212.5,182.08],[197.49,191.27],[182.48000000000002,182.08]]}],"t":33}]}},{"ty":"st","bm":0,"hd":false,"nm":"Stroke","lc":1,"lj":1,"ml":10,"o":{"a":0,"k":100},"w":{"a":0,"k":3},"c":{"a":0,"k":[0.898,0.7412,0.702]}},{"ty":"fl","bm":0,"hd":false,"nm":"Fill","c":{"a":0,"k":[1,1,1]},"r":1,"o":{"a":0,"k":100}},{"ty":"tr","a":{"a":0,"k":[197.4872423223291,181.77914550444112]},"s":{"a":0,"k":[100,100]},"sk":{"a":0,"k":0},"p":{"a":0,"k":[197.4872423223291,181.77914550444112]},"r":{"a":0,"k":0},"sa":{"a":0,"k":0},"o":{"a":0,"k":100}}]},{"ty":"tr","a":{"a":0,"k":[0,0]},"s":{"a":0,"k":[100,100]},"sk":{"a":0,"k":0},"p":{"a":0,"k":[0,0]},"r":{"a":0,"k":0},"sa":{"a":0,"k":0},"o":{"a":0,"k":100}}]},{"ty":"tr","a":{"a":0,"k":[196.9605987168281,186.52214252655415]},"s":{"a":0,"k":[100,100]},"sk":{"a":0,"k":0},"p":{"a":0,"k":[196.9605987168281,186.52214252655415]},"r":{"a":0,"k":0},"sa":{"a":0,"k":0},"o":{"a":0,"k":100}}]},{"ty":"tr","a":{"a":0,"k":[154.95128448532353,186.98853056104008]},"s":{"a":0,"k":[100,100]},"sk":{"a":0,"k":0},"p":{"a":0,"k":[154.95128448532353,186.98853056104008]},"r":{"a":0,"k":0},"sa":{"a":0,"k":0},"o":{"a":0,"k":100}}]},{"ty":"gr","bm":0,"hd":false,"nm":"Hat","it":[{"ty":"gr","bm":0,"hd":false,"nm":"Group 25","it":[{"ty":"el","bm":0,"hd":false,"nm":"Ellipse 9","d":1,"p":{"a":0,"k":[154.45,154.91]},"s":{"a":0,"k":[306.9,5.2]}},{"ty":"st","bm":0,"hd":false,"nm":"Stroke","lc":2,"lj":2,"ml":4,"o":{"a":0,"k":100},"w":{"a":0,"k":2},"c":{"a":0,"k":[0.1529,0.149,0.2667]}},{"ty":"fl","bm":0,"hd":false,"nm":"Fill","c":{"a":0,"k":[0.2353,0.1294,0.3373]},"r":1,"o":{"a":0,"k":100}},{"ty":"tr","a":{"a":0,"k":[0,0]},"s":{"a":0,"k":[100,100]},"sk":{"a":0,"k":0},"p":{"a":0,"k":[0,0]},"r":{"a":0,"k":0},"sa":{"a":0,"k":0},"o":{"a":0,"k":100}}]},{"ty":"gr","bm":0,"hd":false,"nm":"Group 26","it":[{"ty":"sh","bm":0,"hd":false,"nm":"Path 4","d":1,"ks":{"a":0,"k":{"c":true,"i":[[0,0],[0,0],[0,0],[0,0],[0,0],[0,0],[0,0],[0,0]],"o":[[0,0],[0,0],[0,0],[0,0],[0,0],[0,0],[0,0],[0,0]],"v":[[56.05,154.57],[112.95,51.77],[111.67,39.14],[50.02,1],[188.66,30.87],[213.49,61.6],[252.85,154.57],[56.05,154.57]]}}},{"ty":"st","bm":0,"hd":false,"nm":"Stroke","lc":2,"lj":2,"ml":4,"o":{"a":0,"k":100},"w":{"a":0,"k":2},"c":{"a":0,"k":[0.1529,0.149,0.2667]}},{"ty":"fl","bm":0,"hd":false,"nm":"Fill","c":{"a":0,"k":[0.2353,0.1294,0.3373]},"r":1,"o":{"a":0,"k":100}},{"ty":"tr","a":{"a":0,"k":[0,0]},"s":{"a":0,"k":[100,100]},"sk":{"a":0,"k":0},"p":{"a":0,"k":[0,0]},"r":{"a":0,"k":0},"sa":{"a":0,"k":0},"o":{"a":0,"k":100}}]},{"ty":"tr","a":{"a":0,"k":[154.1803113225107,78.94962275287025]},"s":{"a":0,"k":[105,100]},"sk":{"a":0,"k":0},"p":{"a":1,"k":[{"o":{"x":0.167,"y":0.167},"i":{"x":0.833,"y":0.833},"s":[150.1803,78.9496],"t":0},{"o":{"x":0.167,"y":0.167},"i":{"x":0.833,"y":0.833},"s":[170.1803,78.9496],"t":15},{"s":[150.1803,78.9496],"t":33}]},"r":{"a":1,"k":[{"o":{"x":0.167,"y":0.167},"i":{"x":0.833,"y":0.833},"s":[0],"t":0},{"o":{"x":0.167,"y":0.167},"i":{"x":0.833,"y":0.833},"s":[10],"t":15},{"s":[0],"t":33}]},"sa":{"a":0,"k":0},"o":{"a":0,"k":100}}]},{"ty":"gr","bm":0,"hd":false,"nm":"Group 27","it":[{"ty":"gr","bm":0,"hd":false,"nm":"Group 28","it":[{"ty":"sh","bm":0,"hd":false,"nm":"Path 5","d":1,"ks":{"a":0,"k":{"c":false,"i":[[0,0],[13.409999999999997,0],[2.530000000000001,8.890000000000015],[0,0]],"o":[[-2.539999999999992,8.890000000000015],[-13.409999999999997,0],[0,0],[0,0]],"v":[[181.58,236.15],[154.45000000000002,251.73000000000002],[127.32000000000002,236.15],[181.58,236.15]]}}},{"ty":"sh","bm":0,"hd":false,"nm":"Path 6","d":1,"ks":{"a":0,"k":{"c":true,"i":[[0,0],[0,0],[0.480000000000004,-0.6200000000000045],[-0.21000000000000796,-0.75],[-14.240000000000009,0],[-2.8799999999999955,10.079999999999984],[0.46999999999999886,0.6200000000000045],[0.789999999999992,0],[0,0]],"o":[[0,0],[-0.7800000000000011,0],[-0.46999999999999886,0.6299999999999955],[2.8700000000000045,10.080000000000013],[14.240000000000009,0],[0.21999999999999886,-0.75],[-0.46999999999999886,-0.6299999999999955],[0,0],[0,0]],"v":[[181.58,233.65],[127.32000000000002,233.65],[125.32000000000002,234.64000000000001],[124.91000000000003,236.83],[154.44000000000003,254.23000000000002],[183.97000000000003,236.84000000000003],[183.56000000000003,234.65000000000003],[181.56000000000003,233.66000000000003],[181.56000000000003,233.66000000000003]]}}},{"ty":"fl","bm":0,"hd":false,"nm":"Fill","c":{"a":0,"k":[0.898,0.7412,0.702]},"r":1,"o":{"a":0,"k":100}},{"ty":"tr","a":{"a":0,"k":[154.69044109819532,244.10437157689094]},"s":{"a":0,"k":[100,100]},"sk":{"a":0,"k":0},"p":{"a":0,"k":[154.69044109819532,244.10437157689094]},"r":{"a":0,"k":0},"sa":{"a":0,"k":0},"o":{"a":0,"k":100}}]},{"ty":"gr","bm":0,"hd":false,"nm":"Group 29","it":[{"ty":"sh","bm":0,"hd":false,"nm":"Path 8","d":1,"ks":{"a":0,"k":{"c":true,"i":[[0,0],[2.7199999999999847,9.560000000000002],[-0.23000000000000398,0.3100000000000023],[-0.39000000000000057,0],[0,0],[-0.2400000000000091,-0.3199999999999932],[0.11000000000001364,-0.37999999999999545],[13.689999999999998,0]],"o":[[-13.699999999999989,0],[-0.10999999999999943,-0.37999999999999545],[0.23999999999999488,-0.3100000000000023],[0,0],[0.38999999999998636,0],[0.2400000000000091,0.3100000000000023],[-2.7299999999999898,9.550000000000011],[0,0]],"v":[[154.45,252.98],[126.11999999999999,236.48999999999998],[126.32,235.39999999999998],[127.32,234.89999999999998],[181.57999999999998,234.89999999999998],[182.57999999999998,235.39999999999998],[182.77999999999997,236.49999999999997],[154.45,252.98999999999998]]}}},{"ty":"fl","bm":0,"hd":false,"nm":"Fill","c":{"a":0,"k":[1,1,1]},"r":1,"o":{"a":0,"k":100}},{"ty":"tr","a":{"a":0,"k":[0,0]},"s":{"a":0,"k":[100,100]},"sk":{"a":0,"k":0},"p":{"a":0,"k":[0,0]},"r":{"a":0,"k":0},"sa":{"a":0,"k":0},"o":{"a":0,"k":100}}]},{"ty":"tr","a":{"a":0,"k":[154.45,233.98]},"s":{"a":1,"k":[{"o":{"x":0.167,"y":0.167},"i":{"x":0.833,"y":0.833},"s":[72,44],"t":0},{"o":{"x":0.167,"y":0.167},"i":{"x":0.833,"y":0.833},"s":[100,100],"t":10},{"s":[72,44],"t":33}]},"sk":{"a":0,"k":0},"p":{"a":1,"k":[{"o":{"x":0.167,"y":0.167},"i":{"x":0.833,"y":0.833},"s":[154.45,233.98],"t":0},{"o":{"x":0.167,"y":0.167},"i":{"x":0.833,"y":0.833},"s":[154.45,233.98],"t":10},{"s":[154.45,233.98],"t":33}]},"r":{"a":0,"k":0},"sa":{"a":0,"k":0},"o":{"a":0,"k":100}}]},{"ty":"gr","bm":0,"hd":false,"nm":"Group 30","it":[{"ty":"gr","bm":0,"hd":false,"nm":"Group 31","it":[{"ty":"sh","bm":0,"hd":false,"nm":"Path 9","d":1,"ks":{"a":0,"k":{"c":true,"i":[[0,0],[3.280000000000001,-55.43000000000001],[0,0],[19.769999999999982,42.379999999999995],[0,0]],"o":[[7.759999999999991,43.91],[0,0],[-5.720000000000027,-52.97],[0,0],[0,0]],"v":[[213.79,135.79],[218.42999999999998,286.96],[274.59999999999997,274.96],[238.33999999999997,130.45],[213.78999999999996,135.79]]}}},{"ty":"st","bm":0,"hd":false,"nm":"Stroke","lc":2,"lj":2,"ml":4,"o":{"a":0,"k":100},"w":{"a":0,"k":2},"c":{"a":0,"k":[0.1529,0.149,0.2667]}},{"ty":"fl","bm":0,"hd":false,"nm":"Fill","c":{"a":0,"k":[0.2706,0.2706,0.4275]},"r":1,"o":{"a":0,"k":100}},{"ty":"tr","a":{"a":0,"k":[0,0]},"s":{"a":0,"k":[100,100]},"sk":{"a":0,"k":0},"p":{"a":0,"k":[0,0]},"r":{"a":0,"k":0},"sa":{"a":0,"k":0},"o":{"a":0,"k":100}}]},{"ty":"tr","a":{"a":0,"k":[0,0]},"s":{"a":0,"k":[100,100]},"sk":{"a":0,"k":0},"p":{"a":0,"k":[0,0]},"r":{"a":0,"k":0},"sa":{"a":0,"k":0},"o":{"a":0,"k":100}}]},{"ty":"gr","bm":0,"hd":false,"nm":"Group 32","it":[{"ty":"gr","bm":0,"hd":false,"nm":"Group 33","it":[{"ty":"sh","bm":0,"hd":false,"nm":"Path 10","d":1,"ks":{"a":0,"k":{"c":true,"i":[[0,0],[-3.280000000000001,-55.43000000000001],[0,0],[-19.77000000000001,42.379999999999995],[0,0]],"o":[[-7.760000000000005,43.91],[0,0],[5.719999999999999,-52.97],[0,0],[0,0]],"v":[[95.11,135.79],[90.47,286.96],[34.3,274.96],[70.56,130.45],[95.11,135.79]]}}},{"ty":"st","bm":0,"hd":false,"nm":"Stroke","lc":2,"lj":2,"ml":4,"o":{"a":0,"k":100},"w":{"a":0,"k":2},"c":{"a":0,"k":[0.1529,0.149,0.2667]}},{"ty":"fl","bm":0,"hd":false,"nm":"Fill","c":{"a":0,"k":[0.2706,0.2706,0.4275]},"r":1,"o":{"a":0,"k":100}},{"ty":"tr","a":{"a":0,"k":[0,0]},"s":{"a":0,"k":[100,100]},"sk":{"a":0,"k":0},"p":{"a":0,"k":[0,0]},"r":{"a":0,"k":0},"sa":{"a":0,"k":0},"o":{"a":0,"k":100}}]},{"ty":"tr","a":{"a":0,"k":[64.43469217816708,287.83347180023304]},"s":{"a":0,"k":[100,114]},"sk":{"a":0,"k":0},"p":{"a":0,"k":[64.43469217816708,298.9030922452135]},"r":{"a":0,"k":0},"sa":{"a":0,"k":0},"o":{"a":0,"k":100}}]},{"ty":"gr","bm":0,"hd":false,"nm":"Group 34","it":[{"ty":"gr","bm":0,"hd":false,"nm":"Group 35","it":[{"ty":"gr","bm":0,"hd":false,"nm":"Group 36","it":[{"ty":"sh","bm":0,"hd":false,"nm":"Path 11","d":1,"ks":{"a":0,"k":{"c":true,"i":[[0,0],[0,0],[2.640000000000015,0],[0,0],[-0.5500000000000114,3.219999999999999],[0,0],[-1.5800000000000125,0],[0,0],[-0.3300000000000125,-1.9300000000000068]],"o":[[0,0],[0.5500000000000114,3.2299999999999898],[0,0],[-2.6399999999999864,0],[0,0],[0.3300000000000125,-1.9399999999999977],[0,0],[1.5800000000000125,0],[0,0]],"v":[[161.31,186.88],[166.83,219.42],[162.77,225.67999999999998],[146.12,225.67999999999998],[142.06,219.42],[147.58,186.88],[150.86,183.56],[158.02,183.56],[161.3,186.88]]}}},{"ty":"st","bm":0,"hd":false,"nm":"Stroke","lc":2,"lj":2,"ml":4,"o":{"a":0,"k":100},"w":{"a":0,"k":2},"c":{"a":0,"k":[0.8667,0.651,0.6118]}},{"ty":"fl","bm":0,"hd":false,"nm":"Fill","c":{"a":0,"k":[0.898,0.7412,0.702]},"r":1,"o":{"a":0,"k":100}},{"ty":"tr","a":{"a":0,"k":[0,0]},"s":{"a":0,"k":[100,100]},"sk":{"a":0,"k":0},"p":{"a":0,"k":[0,0]},"r":{"a":0,"k":0},"sa":{"a":0,"k":0},"o":{"a":0,"k":100}}]},{"ty":"tr","a":{"a":0,"k":[0,0]},"s":{"a":0,"k":[100,100]},"sk":{"a":0,"k":0},"p":{"a":0,"k":[0,0]},"r":{"a":0,"k":0},"sa":{"a":0,"k":0},"o":{"a":0,"k":100}}]},{"ty":"gr","bm":0,"hd":false,"nm":"Group 37","it":[{"ty":"gr","bm":0,"hd":false,"nm":"Group 38","it":[{"ty":"el","bm":0,"hd":false,"nm":"Ellipse 10","d":1,"p":{"a":0,"k":[112.32,200.17]},"s":{"a":0,"k":[3.92,3.92]}},{"ty":"fl","bm":0,"hd":false,"nm":"Fill","c":{"a":0,"k":[0.6078,0.5333,0.4078]},"r":1,"o":{"a":0,"k":100}},{"ty":"tr","a":{"a":0,"k":[0,0]},"s":{"a":0,"k":[100,100]},"sk":{"a":0,"k":0},"p":{"a":0,"k":[0,0]},"r":{"a":0,"k":0},"sa":{"a":0,"k":0},"o":{"a":0,"k":100}}]},{"ty":"gr","bm":0,"hd":false,"nm":"Group 39","it":[{"ty":"el","bm":0,"hd":false,"nm":"Ellipse 11","d":1,"p":{"a":0,"k":[117.74,205.98]},"s":{"a":0,"k":[3.92,3.92]}},{"ty":"fl","bm":0,"hd":false,"nm":"Fill","c":{"a":0,"k":[0.6078,0.5333,0.4078]},"r":1,"o":{"a":0,"k":100}},{"ty":"tr","a":{"a":0,"k":[0,0]},"s":{"a":0,"k":[100,100]},"sk":{"a":0,"k":0},"p":{"a":0,"k":[0,0]},"r":{"a":0,"k":0},"sa":{"a":0,"k":0},"o":{"a":0,"k":100}}]},{"ty":"gr","bm":0,"hd":false,"nm":"Group 40","it":[{"ty":"el","bm":0,"hd":false,"nm":"Ellipse 12","d":1,"p":{"a":0,"k":[123.17,200.17]},"s":{"a":0,"k":[3.92,3.92]}},{"ty":"fl","bm":0,"hd":false,"nm":"Fill","c":{"a":0,"k":[0.6078,0.5333,0.4078]},"r":1,"o":{"a":0,"k":100}},{"ty":"tr","a":{"a":0,"k":[0,0]},"s":{"a":0,"k":[100,100]},"sk":{"a":0,"k":0},"p":{"a":0,"k":[0,0]},"r":{"a":0,"k":0},"sa":{"a":0,"k":0},"o":{"a":0,"k":100}}]},{"ty":"gr","bm":0,"hd":false,"nm":"Group 41","it":[{"ty":"el","bm":0,"hd":false,"nm":"Ellipse 13","d":1,"p":{"a":0,"k":[185.72,199.22]},"s":{"a":0,"k":[3.92,3.92]}},{"ty":"fl","bm":0,"hd":false,"nm":"Fill","c":{"a":0,"k":[0.6078,0.5333,0.4078]},"r":1,"o":{"a":0,"k":100}},{"ty":"tr","a":{"a":0,"k":[0,0]},"s":{"a":0,"k":[100,100]},"sk":{"a":0,"k":0},"p":{"a":0,"k":[0,0]},"r":{"a":0,"k":0},"sa":{"a":0,"k":0},"o":{"a":0,"k":100}}]},{"ty":"gr","bm":0,"hd":false,"nm":"Group 42","it":[{"ty":"el","bm":0,"hd":false,"nm":"Ellipse 14","d":1,"p":{"a":0,"k":[191.15,205.03]},"s":{"a":0,"k":[3.92,3.92]}},{"ty":"fl","bm":0,"hd":false,"nm":"Fill","c":{"a":0,"k":[0.6078,0.5333,0.4078]},"r":1,"o":{"a":0,"k":100}},{"ty":"tr","a":{"a":0,"k":[0,0]},"s":{"a":0,"k":[100,100]},"sk":{"a":0,"k":0},"p":{"a":0,"k":[0,0]},"r":{"a":0,"k":0},"sa":{"a":0,"k":0},"o":{"a":0,"k":100}}]},{"ty":"gr","bm":0,"hd":false,"nm":"Group 43","it":[{"ty":"el","bm":0,"hd":false,"nm":"Ellipse 15","d":1,"p":{"a":0,"k":[196.57,199.22]},"s":{"a":0,"k":[3.92,3.92]}},{"ty":"fl","bm":0,"hd":false,"nm":"Fill","c":{"a":0,"k":[0.6078,0.5333,0.4078]},"r":1,"o":{"a":0,"k":100}},{"ty":"tr","a":{"a":0,"k":[0,0]},"s":{"a":0,"k":[100,100]},"sk":{"a":0,"k":0},"p":{"a":0,"k":[0,0]},"r":{"a":0,"k":0},"sa":{"a":0,"k":0},"o":{"a":0,"k":100}}]},{"ty":"tr","a":{"a":0,"k":[0,0]},"s":{"a":0,"k":[100,100]},"sk":{"a":0,"k":0},"p":{"a":0,"k":[0,0]},"r":{"a":0,"k":0},"sa":{"a":0,"k":0},"o":{"a":0,"k":100}}]},{"ty":"gr","bm":0,"hd":false,"nm":"Group 44","it":[{"ty":"gr","bm":0,"hd":false,"nm":"Group 45","it":[{"ty":"el","bm":0,"hd":false,"nm":"Ellipse 16","d":1,"p":{"a":0,"k":[198.08,210.41]},"s":{"a":0,"k":[36.08,24.4]}},{"ty":"fl","bm":0,"hd":false,"nm":"Fill","c":{"a":0,"k":[0.9294,0.6157,0.7373]},"r":1,"o":{"a":0,"k":100}},{"ty":"tr","a":{"a":0,"k":[0,0]},"s":{"a":0,"k":[100,100]},"sk":{"a":0,"k":0},"p":{"a":0,"k":[0,0]},"r":{"a":0,"k":0},"sa":{"a":0,"k":0},"o":{"a":0,"k":64}}]},{"ty":"gr","bm":0,"hd":false,"nm":"Group 46","it":[{"ty":"el","bm":0,"hd":false,"nm":"Ellipse 17","d":1,"p":{"a":0,"k":[110.81,210.41]},"s":{"a":0,"k":[36.08,24.4]}},{"ty":"fl","bm":0,"hd":false,"nm":"Fill","c":{"a":0,"k":[0.9294,0.6157,0.7373]},"r":1,"o":{"a":0,"k":100}},{"ty":"tr","a":{"a":0,"k":[0,0]},"s":{"a":0,"k":[100,100]},"sk":{"a":0,"k":0},"p":{"a":0,"k":[0,0]},"r":{"a":0,"k":0},"sa":{"a":0,"k":0},"o":{"a":0,"k":64}}]},{"ty":"tr","a":{"a":0,"k":[0,0]},"s":{"a":0,"k":[100,100]},"sk":{"a":0,"k":0},"p":{"a":0,"k":[0,0]},"r":{"a":0,"k":0},"sa":{"a":0,"k":0},"o":{"a":0,"k":100}}]},{"ty":"gr","bm":0,"hd":false,"nm":"Group 47","it":[{"ty":"gr","bm":0,"hd":false,"nm":"Group 48","it":[{"ty":"el","bm":0,"hd":false,"nm":"Ellipse 18","d":1,"p":{"a":0,"k":[154.45,179.85]},"s":{"a":0,"k":[166.22,202.98]}},{"ty":"st","bm":0,"hd":false,"nm":"Stroke","lc":1,"lj":1,"ml":10,"o":{"a":0,"k":100},"w":{"a":0,"k":3},"c":{"a":0,"k":[0.898,0.7412,0.702]}},{"ty":"fl","bm":0,"hd":false,"nm":"Fill","c":{"a":0,"k":[0.949,0.8549,0.8275]},"r":1,"o":{"a":0,"k":100}},{"ty":"tr","a":{"a":0,"k":[0,0]},"s":{"a":0,"k":[100,100]},"sk":{"a":0,"k":0},"p":{"a":0,"k":[0,0]},"r":{"a":0,"k":0},"sa":{"a":0,"k":0},"o":{"a":0,"k":100}}]},{"ty":"tr","a":{"a":0,"k":[0,0]},"s":{"a":0,"k":[100,100]},"sk":{"a":0,"k":0},"p":{"a":0,"k":[0,0]},"r":{"a":0,"k":0},"sa":{"a":0,"k":0},"o":{"a":0,"k":100}}]},{"ty":"tr","a":{"a":0,"k":[0,0]},"s":{"a":0,"k":[100,100]},"sk":{"a":0,"k":0},"p":{"a":0,"k":[0,0]},"r":{"a":0,"k":0},"sa":{"a":0,"k":0},"o":{"a":0,"k":100}}]},{"ty":"gr","bm":0,"hd":false,"nm":"Group 49","it":[{"ty":"gr","bm":0,"hd":false,"nm":"Group 50","it":[{"ty":"sh","bm":0,"hd":false,"nm":"Path 12","d":1,"ks":{"a":0,"k":{"c":true,"i":[[0,0],[0,0],[0,0],[0,0]],"o":[[0,0],[0,0],[0,0],[0,0]],"v":[[241.4,265.26],[183.57,267.55],[226.6,215.91],[241.4,265.26]]}}},{"ty":"st","bm":0,"hd":false,"nm":"Stroke","lc":2,"lj":2,"ml":4,"o":{"a":0,"k":100},"w":{"a":0,"k":2},"c":{"a":0,"k":[0.1529,0.149,0.2667]}},{"ty":"fl","bm":0,"hd":false,"nm":"Fill","c":{"a":0,"k":[0.1529,0.149,0.2667]},"r":1,"o":{"a":0,"k":100}},{"ty":"tr","a":{"a":0,"k":[0,0]},"s":{"a":0,"k":[100,100]},"sk":{"a":0,"k":0},"p":{"a":0,"k":[0,0]},"r":{"a":0,"k":0},"sa":{"a":0,"k":0},"o":{"a":0,"k":100}}]},{"ty":"tr","a":{"a":0,"k":[0,0]},"s":{"a":0,"k":[100,100]},"sk":{"a":0,"k":0},"p":{"a":0,"k":[0,0]},"r":{"a":0,"k":0},"sa":{"a":0,"k":0},"o":{"a":0,"k":100}}]},{"ty":"gr","bm":0,"hd":false,"nm":"Group 51","it":[{"ty":"gr","bm":0,"hd":false,"nm":"Group 52","it":[{"ty":"sh","bm":0,"hd":false,"nm":"Path 13","d":1,"ks":{"a":0,"k":{"c":true,"i":[[0,0],[0,0],[0,0],[0,0]],"o":[[0,0],[0,0],[0,0],[0,0]],"v":[[67.49,265.26],[125.32,267.55],[82.3,215.91],[67.49,265.26]]}}},{"ty":"st","bm":0,"hd":false,"nm":"Stroke","lc":2,"lj":2,"ml":4,"o":{"a":0,"k":100},"w":{"a":0,"k":2},"c":{"a":0,"k":[0.1529,0.149,0.2667]}},{"ty":"fl","bm":0,"hd":false,"nm":"Fill","c":{"a":0,"k":[0.1529,0.149,0.2667]},"r":1,"o":{"a":0,"k":100}},{"ty":"tr","a":{"a":0,"k":[0,0]},"s":{"a":0,"k":[100,100]},"sk":{"a":0,"k":0},"p":{"a":0,"k":[0,0]},"r":{"a":0,"k":0},"sa":{"a":0,"k":0},"o":{"a":0,"k":100}}]},{"ty":"tr","a":{"a":0,"k":[0,0]},"s":{"a":0,"k":[100,100]},"sk":{"a":0,"k":0},"p":{"a":0,"k":[0,0]},"r":{"a":0,"k":0},"sa":{"a":0,"k":0},"o":{"a":0,"k":100}}]}],"ind":1},{"ty":4,"nm":"Ellipse 1","sr":1,"st":0,"op":150,"ip":0,"hd":false,"ddd":0,"bm":0,"hasMask":false,"ao":0,"ks":{"a":{"a":0,"k":[0,0]},"s":{"a":0,"k":[101.9821,101.9821]},"sk":{"a":0,"k":0},"p":{"a":0,"k":[250,250]},"r":{"a":0,"k":0},"sa":{"a":0,"k":0},"o":{"a":0,"k":100}},"shapes":[{"ty":"el","bm":0,"hd":false,"nm":"Ellipse Path 1","d":1,"p":{"a":0,"k":[0,0]},"s":{"a":0,"k":[284,284]}},{"ty":"fl","bm":0,"hd":false,"nm":"Fill","c":{"a":0,"k":[0.851,0.8784,0.8863]},"r":2,"o":{"a":0,"k":100}}],"ind":2}],"v":"5.7.0","fr":30,"op":150,"ip":0,"assets":[]}